dgc_pricecharting_ingest/bs.py
dgc_pricecharting_ingest/db.py
dgc_pricecharting_ingest/handlers.py
dgc_pricecharting_ingest/img.py
dgc_pricecharting_ingest/pricecharting.py
dgc_pricecharting_ingest/url.py
dgc_pricecharting_ingest/uuid.py
dgc_pricecharting_ingest-1.0.2.dist-info/METADATA
dgc_pricecharting_ingest-1.0.2.dist-info/WHEEL
dgc_pricecharting_ingest-1.0.2.dist-info/top_level.txt
dgc_pricecharting_ingest-1.0.2.dist-info/RECORD
