Metadata-Version: 2.4
Name: dgc_pricecharting_ingest
Version: 1.0.2
Author-email: velopace <velopace7@gmail.com>
License: MIT
Requires-Dist: functions-framework==3.*
Requires-Dist: flask==3.*
Requires-Dist: firebase-admin==6.6.0
Requires-Dist: opticedge-cloud-utils==1.0.9
Requires-Dist: opticedge-types==1.0.16
Requires-Dist: beautifulsoup4==4.14.2
Requires-Dist: requests==2.32.5
Provides-Extra: dev
Requires-Dist: build>=1.3.0; extra == "dev"
Requires-Dist: coverage>=7.10.2; extra == "dev"
Requires-Dist: pytest>=8.4.1; extra == "dev"
Requires-Dist: pytest-cov>=6.2.1; extra == "dev"
Requires-Dist: twine>=6.1.0; extra == "dev"
Requires-Dist: toml>=0.10.2; extra == "dev"
